simple_repr/__init__.py
simple_repr/simple_repr.py
simple_repr-1.3.0.dist-info/LICENSE.md
simple_repr-1.3.0.dist-info/METADATA
simple_repr-1.3.0.dist-info/WHEEL
simple_repr-1.3.0.dist-info/top_level.txt
simple_repr-1.3.0.dist-info/RECORD
