Metadata-Version: 2.1
Name: simple-repr
Version: 1.3.0
Summary: SimpleRepr is a class for creating string representations of classes.
Home-page: https://github.com/mr-strawberry66/python-repr-generation
Author: Sam Kenney
Author-email: sam.kenney@me.com
License: MIT
Platform: UNKNOWN
